okta_jwt/__init__.py
okta_jwt/exceptions.py
okta_jwt/jwt.py
okta_jwt/utils.py
okta_jwt-1.1.2.dist-info/LICENSE
okta_jwt-1.1.2.dist-info/METADATA
okta_jwt-1.1.2.dist-info/WHEEL
okta_jwt-1.1.2.dist-info/top_level.txt
okta_jwt-1.1.2.dist-info/RECORD
