Metadata-Version: 2.1
Name: okta-jwt
Version: 1.1.2
Summary: Okta JWT Access Token verifier
Home-page: https://github.com/adithyasampatoor/okta_jwt
Author: Adithya Sampatoor
Author-email: adithya.sampatoor@gmail.com
License: UNKNOWN
Platform: UNKNOWN
Classifier: Development Status :: 5 - Production/Stable
Classifier: Intended Audience :: Developers
Classifier: Natural Language :: English
Classifier: License :: OSI Approved :: MIT License
Classifier: Programming Language :: Python :: 3.6
Classifier: Programming Language :: Python :: Implementation :: PyPy
Classifier: Topic :: Utilities
Requires-Dist: six (<2.0)
Requires-Dist: requests
Requires-Dist: python-jose
